mp_nerf/__init__.py
mp_nerf/kb_proteins.py
mp_nerf/massive_pnerf.py
mp_nerf/ml_utils.py
mp_nerf/proteins.py
mp_nerf/utils.py
mp_nerf-1.0.3.dist-info/LICENSE
mp_nerf-1.0.3.dist-info/METADATA
mp_nerf-1.0.3.dist-info/WHEEL
mp_nerf-1.0.3.dist-info/top_level.txt
mp_nerf-1.0.3.dist-info/RECORD
