Metadata-Version: 2.1
Name: mp-nerf
Version: 1.0.3
Summary: MP-NeRF: Massively Parallel Natural Extension of Reference Frame
Home-page: https://github.com/eleutherAI/mp_nerf
Author: Eric Alcaide
Author-email: ericalcaide1@gmail.com
License: MIT
Keywords: computational biolgy,bioinformatics,machine learning
Platform: UNKNOWN
Classifier: Development Status :: 4 - Beta
Classifier: Intended Audience :: Developers
Classifier: Topic :: Scientific/Engineering :: Artificial Intelligence
Classifier: License :: OSI Approved :: MIT License
Classifier: Programming Language :: Python :: 3.6
Requires-Dist: einops (>=0.3)
Requires-Dist: numpy
Requires-Dist: torch (>=1.6)
